setup.cfg
setup.py
cgi_wsgi/__init__.py
cgi_wsgi.egg-info/PKG-INFO
cgi_wsgi.egg-info/SOURCES.txt
cgi_wsgi.egg-info/dependency_links.txt
cgi_wsgi.egg-info/not-zip-safe
cgi_wsgi.egg-info/top_level.txt