Metadata-Version: 1.1
Name: cgi-wsgi
Version: 0.1
Summary: A CGI-like http interface for WSGI (for educational purposes only)
Home-page: http://github.com/red56/cgi_wsgi
Author: Tim Diggins
Author-email: tim@red56.co.uk
License: MIT
Download-URL: https://github.com/red56/cgi_wsgi/tarball/v0.1
Platform: UNKNOWN
